breesy/Event.py
breesy/RecordingMetadata.py
breesy/__init__.py
breesy/breesy_scipy.py
breesy/breesy_sklearn.py
breesy/case_insensitive_dict.py
breesy/constants.py
breesy/data.py
breesy/errors.py
breesy/events.py
breesy/features.py
breesy/filtering.py
breesy/load.py
breesy/load_brainvision.py
breesy/load_events.py
breesy/log.py
breesy/playground.py
breesy/plots.py
breesy/processing.py
breesy/recording.py
breesy/type_hints.py
breesy-0.3.10.dist-info/METADATA
breesy-0.3.10.dist-info/WHEEL
breesy-0.3.10.dist-info/top_level.txt
breesy-0.3.10.dist-info/RECORD
